tfmesos2/__init__.py
tfmesos2/scheduler.py
tfmesos2/server.py
tfmesos2-0.3.0.dist-info/METADATA
tfmesos2-0.3.0.dist-info/WHEEL
tfmesos2-0.3.0.dist-info/top_level.txt
tfmesos2-0.3.0.dist-info/RECORD
