Metadata-Version: 2.1
Name: tfmesos2
Version: 0.3.0
Summary: Tensorflow for Apache Mesos
Home-page: https://www.aventer.biz/
Author: Andreas Peters
Author-email: support@aventer.biz
License: Apache License 2.0
Requires-Python: >=3.6
Requires-Dist: avmesos>=0.4.0
Requires-Dist: addict>=2.4.0
Requires-Dist: flask>=3.0.0
Requires-Dist: flask-httpauth>=4.0.0
Requires-Dist: waitress>=2.1.0
